[
  {
    "day": "2026-05-16",
    "weatherMode": "sunny",
    "startTime": "10:00",
    "endTime": "11:00",
    "title": "開会セレモニー",
    "area": "屋外メイン",
    "location": "メインステージ",
    "description": "2日間の海王祭スタートを告げるオープニングです。",
    "organization": "実行委員会",
    "published": true,
    "image": "events/placeholder.png"
  },
  {
    "day": "2026-05-16",
    "weatherMode": "sunny",
    "startTime": "11:00",
    "endTime": "12:00",
    "title": "バンドライブ",
    "area": "屋外メイン",
    "location": "メインステージ",
    "description": "学生バンドによるライブパフォーマンス",
    "organization": "軽音サークル連合",
    "published": true,
    "image": "events/placeholder.png"
  },
  {
    "day": "2026-05-16",
    "weatherMode": "sunny",
    "startTime": "12:00",
    "endTime": "13:00",
    "title": "研究室公開",
    "area": "講義棟",
    "location": "海象系研究室",
    "description": "海洋系研究の展示と学生による解説を行います。",
    "organization": "研究室有志",
    "published": true,
    "image": "events/placeholder.png"
  },
  {
    "day": "2026-05-16",
    "weatherMode": "sunny",
    "startTime": "13:00",
    "endTime": "14:00",
    "title": "ダンスパフォーマンス",
    "area": "屋外メイン",
    "location": "メインステージ",
    "description": "ダンスサークルによるパフォーマンス",
    "organization": "ダンスサークル",
    "published": true,
    "image": "events/placeholder.png"
  },
  {
    "day": "2026-05-16",
    "weatherMode": "rainy",
    "startTime": "14:00",
    "endTime": "15:00",
    "title": "プログラミング体験",
    "area": "講義棟",
    "location": "情報系教室",
    "description": "雨天時は講義棟教室で体験ブースを実施します。",
    "organization": "プログラミング研究会",
    "published": true,
    "image": "events/placeholder.png"
  },
  {
    "day": "2026-05-16",
    "weatherMode": "rainy",
    "startTime": "15:00",
    "endTime": "16:00",
    "title": "海のクイズ大会",
    "area": "講義棟",
    "location": "大講義室",
    "description": "参加者全員で楽しむクイズ大会",
    "organization": "クイズ研究会",
    "published": true,
    "image": "events/placeholder.png"
  },
  {
    "day": "2026-05-16",
    "weatherMode": "rainy",
    "startTime": "16:00",
    "endTime": "17:00",
    "title": "アコースティックライブ",
    "area": "体育館",
    "location": "メインアリーナ",
    "description": "雨天プログラムとして体育館でライブを開催。",
    "organization": "アコースティック部門",
    "published": true,
    "image": "events/placeholder.png"
  },
  {
    "day": "2026-05-17",
    "weatherMode": "sunny",
    "startTime": "10:00",
    "endTime": "11:30",
    "title": "2日目オープニング",
    "area": "屋外メイン",
    "location": "メインステージ",
    "description": "2日目の見どころ紹介と朝の挨拶。",
    "organization": "実行委員会",
    "published": true,
    "image": "events/placeholder.png"
  },
  {
    "day": "2026-05-17",
    "weatherMode": "sunny",
    "startTime": "11:30",
    "endTime": "13:00",
    "title": "マグロ解体ショー",
    "area": "中庭",
    "location": "特設ステージ",
    "description": "海洋大ならではの人気企画です。",
    "organization": "水産系有志",
    "published": true,
    "image": "events/placeholder.png"
  },
  {
    "day": "2026-05-17",
    "weatherMode": "sunny",
    "startTime": "13:00",
    "endTime": "14:00",
    "title": "模擬店食べ歩きラリー",
    "area": "キャンパス",
    "location": "模擬店エリア",
    "description": "対象店舗を回ってスタンプを集めよう。",
    "organization": "模擬店連合",
    "published": true,
    "image": "events/placeholder.png"
  },
  {
    "day": "2026-05-17",
    "weatherMode": "rainy",
    "startTime": "14:00",
    "endTime": "15:30",
    "title": "海の生き物トーク",
    "area": "講義棟",
    "location": "大会議室",
    "description": "先生と学生によるトークセッション。",
    "organization": "生物系サークル",
    "published": true,
    "image": "events/placeholder.png"
  },
  {
    "day": "2026-05-17",
    "weatherMode": "rainy",
    "startTime": "15:30",
    "endTime": "18:00",
    "title": "クロージング",
    "area": "体育館",
    "location": "メインアリーナ",
    "description": "2日間の締めくくり企画です。",
    "organization": "実行委員会",
    "published": true,
    "image": "events/placeholder.png"
  }
]
